src/__about__.py
src/__init__.py
src/dialoget.py
dialoget-0.3.0.dist-info/METADATA
dialoget-0.3.0.dist-info/WHEEL
dialoget-0.3.0.dist-info/licenses/LICENSE
dialoget-0.3.0.dist-info/RECORD
