Metadata-Version: 2.1
Name: dialoget
Version: 0.3.0
Summary: A Sentence Python decorator for displaying dynamic log messages.
Project-URL: Documentation, https://github.com/dialoget/py#readme
Project-URL: Issues, https://github.com/dialoget/py/issues
Project-URL: Source, https://github.com/dialoget/py
Author-email: Tom Sapletta <tom@sapletta.com>
License-Expression: Apache-2.0
License-File: LICENSE
Keywords: Sentence,console,dialogware,framework,terminal,test,time
Classifier: Development Status :: 4 - Beta
Classifier: Programming Language :: Python
Classifier: Programming Language :: Python :: 3.7
Classifier: Programming Language :: Python :: 3.8
Classifier: Programming Language :: Python :: 3.9
Classifier: Programming Language :: Python :: 3.10
Classifier: Programming Language :: Python :: 3.11
Classifier: Programming Language :: Python :: Implementation :: CPython
Classifier: Programming Language :: Python :: Implementation :: PyPy
Requires-Python: >=3.7
